{"id":1111,"page":1111,"slug":"when-you-are-leaving-home-for-the-first-time","title":"When you are leaving home for the first time.","titleHi":"जब आप पहली बार घर छोड़ रहे हैं।","imageUrl":"1111_low.gif","ampImage":"1111.gif","url":"https://gif-api.askgif.com/gif/id/1111-en.json","dateCreated":"2020-04-25T17:19:26.453Z","dateModified":"0001-01-01T00:00:00","contributedBy":"AskGif","tags":[{"slug":"actress","name":"actress"},{"slug":"boarding-school","name":"boarding-school"},{"slug":"georgie-henley","name":"georgie-henley"},{"slug":"hollywood","name":"hollywood"},{"slug":"leaving","name":"leaving"},{"slug":"memories","name":"memories"},{"slug":"sad","name":"sad"}]}