{"id":1233,"page":1233,"slug":"when-you-just-came-out-of-beauty-parlor","title":"When you just came out of beauty parlor","titleHi":"जब आप अभी-अभी ब्यूटी पार्लर से निकली हैं","imageUrl":"1233_low.gif","ampImage":"1233.gif","url":"https://gif-api.askgif.com/gif/id/1233-en.json","dateCreated":"2020-05-02T11:49:55.743Z","dateModified":"0001-01-01T00:00:00","contributedBy":"AskGif","tags":[{"slug":"actress","name":"actress"},{"slug":"bonnie-wright","name":"bonnie-wright"},{"slug":"hollywood","name":"hollywood"},{"slug":"open-hair","name":"open-hair"}]}