{"id":1319,"page":1319,"slug":"i-dont-know-those-people.-i-wanna-go-home","title":"I don't know those people. I wanna go home.","titleHi":"मैं उन लोगों को नहीं जानता। ","imageUrl":"1319_low.gif","ampImage":"1319.gif","url":"https://gif-api.askgif.com/gif/id/1319-en.json","dateCreated":"2020-08-14T16:38:38.472Z","dateModified":"0001-01-01T00:00:00","contributedBy":"AskGif","tags":[{"slug":"dont-know","name":"dont-know"},{"slug":"fear","name":"fear"},{"slug":"feared","name":"feared"},{"slug":"home-alone","name":"home-alone"},{"slug":"leave-me","name":"leave-me"},{"slug":"leave-me-alone","name":"leave-me-alone"},{"slug":"miss","name":"miss"},{"slug":"quotes","name":"quotes"},{"slug":"sad","name":"sad"},{"slug":"scared","name":"scared"},{"slug":"sweet-home","name":"sweet-home"}]}