{"id":1382,"page":1382,"slug":"i-want-you-only-you","title":"I want you, only you.!","titleHi":"मैं केवल तुम्हें चाहता हूँ।!","imageUrl":"1382_low.gif","ampImage":"1382.gif","url":"https://gif-api.askgif.com/gif/id/1382-en.json","dateCreated":"2020-08-17T02:58:27.363Z","dateModified":"0001-01-01T00:00:00","contributedBy":"sumitc91","tags":[{"slug":"honest","name":"honest"},{"slug":"i-love-you","name":"i-love-you"},{"slug":"in-love","name":"in-love"},{"slug":"love","name":"love"},{"slug":"only-you","name":"only-you"},{"slug":"single-partner","name":"single-partner"}]}