{"id":145,"page":145,"slug":"when-your-friend-challenge-you-to-make-someone-fool-on-april-fool-day","title":"When your friend challenge you to make someone fool on April fool day.","titleHi":"जब आपका मित्र आपको अप्रैल मूर्ख दिन पर मूर्ख बनाने के लिए चुनौती देता है।","imageUrl":"145_low.gif","ampImage":"145.gif","url":"https://gif-api.askgif.com/gif/id/145-en.json","dateCreated":"2018-06-29T18:14:02.858Z","dateModified":"0001-01-01T00:00:00","contributedBy":"AskGif","tags":[{"slug":"actress","name":"actress"},{"slug":"hannah-montana","name":"hannah-montana"},{"slug":"miley-cyrus","name":"miley-cyrus"},{"slug":"singer","name":"singer"},{"slug":"smile","name":"smile"},{"slug":"wink","name":"wink"}]}