{"id":163,"page":163,"slug":"when-the-recipe-says-chill-in-the-fridge-for-an-hour","title":"When the recipe says 'Chill in the fridge for an hour.'","titleHi":"जब नुस्खा कहता है \"एक घंटे के लिए फ्रिज में ठंडा करें।\"","imageUrl":"163_low.gif","ampImage":"163.gif","url":"https://gif-api.askgif.com/gif/id/163-en.json","dateCreated":"2018-07-02T18:41:00.772Z","dateModified":"0001-01-01T00:00:00","contributedBy":"AskGif","tags":[{"slug":"bye","name":"bye"},{"slug":"chilling","name":"chilling"},{"slug":"fridge","name":"fridge"},{"slug":"hiding","name":"hiding"},{"slug":"hungry","name":"hungry"}]}