{"id":192,"page":192,"slug":"this-is-how-i-tease-my-sister-after-knowing-her-secrets","title":"This is how i tease my sister after knowing her secrets.","titleHi":"जब मैं अपने रहस्यों को जानता हूं तो मैं अपनी बहन को चिढ़ाता हूं।","imageUrl":"192_low.gif","ampImage":"192.gif","url":"https://gif-api.askgif.com/gif/id/192-en.json","dateCreated":"2018-07-08T16:10:41.75Z","dateModified":"0001-01-01T00:00:00","contributedBy":"AskGif","tags":[{"slug":"flirt","name":"flirt"},{"slug":"girl","name":"girl"},{"slug":"lip","name":"lip"},{"slug":"lip-bite","name":"lip-bite"},{"slug":"sister","name":"sister"},{"slug":"tease","name":"tease"}]}