{"id":206,"page":206,"slug":"when-you-find-something-interesting-in-middle-of-your-work","title":"When  you find something interesting in middle of your work.","titleHi":"जब आपको अपने काम के बीच में कुछ दिलचस्प लगता है।","imageUrl":"206_low.gif","ampImage":"206.gif","url":"https://gif-api.askgif.com/gif/id/206-en.json","dateCreated":"2018-07-10T19:14:17.728Z","dateModified":"0001-01-01T00:00:00","contributedBy":"AskGif","tags":[{"slug":"beach","name":"beach"},{"slug":"bikini","name":"bikini"},{"slug":"child","name":"child"},{"slug":"distraction","name":"distraction"},{"slug":"interesting","name":"interesting"},{"slug":"stare","name":"stare"}]}