{"id":217,"page":217,"slug":"getting-ready-for-the-first-date","title":"Getting ready for the first date.","titleHi":"पहली तारीख के लिए तैयार हो रही है।","imageUrl":"217_low.gif","ampImage":"217.gif","url":"https://gif-api.askgif.com/gif/id/217-en.json","dateCreated":"2018-07-15T08:17:08.109Z","dateModified":"0001-01-01T00:00:00","contributedBy":"AskGif","tags":[{"slug":"bath","name":"bath"},{"slug":"dating","name":"dating"},{"slug":"girl","name":"girl"},{"slug":"naked","name":"naked"},{"slug":"nude","name":"nude"},{"slug":"shave","name":"shave"}]}