{"id":460,"page":460,"slug":"dont-cry-because-its-over.-smile-because-it-happened","title":"Don't cry because it's over. Smile because it happened.","titleHi":"रोओ मत क्योंकि यह खत्म हो गया है। मुस्कुराओ क्योंकि यह होता है।","imageUrl":"460_low.gif","ampImage":"460.gif","url":"https://gif-api.askgif.com/gif/id/460-en.json","dateCreated":"2018-10-05T16:05:03.01Z","dateModified":"0001-01-01T00:00:00","contributedBy":"AskGif","tags":[{"slug":"a-star-is-born","name":"a-star-is-born"},{"slug":"break-up","name":"break-up"},{"slug":"fake-smile","name":"fake-smile"},{"slug":"hollywood","name":"hollywood"},{"slug":"lady-gaga","name":"lady-gaga"},{"slug":"new-movies","name":"new-movies"},{"slug":"quotes","name":"quotes"},{"slug":"smile","name":"smile"},{"slug":"smile-quotes","name":"smile-quotes"}]}