{"id":547,"page":547,"slug":"trying-to-stay-awake-in-class","title":"Trying to stay awake in class.","titleHi":"कक्षा में जागते रहने की कोशिश करना।","imageUrl":"547_low.gif","ampImage":"547.gif","url":"https://gif-api.askgif.com/gif/id/547-en.json","dateCreated":"2019-02-23T10:18:39.107Z","dateModified":"0001-01-01T00:00:00","contributedBy":"AskGif","tags":[{"slug":"animation","name":"animation"},{"slug":"cartoon","name":"cartoon"},{"slug":"class","name":"class"},{"slug":"sleep","name":"sleep"},{"slug":"sleepy","name":"sleepy"},{"slug":"tom","name":"tom"},{"slug":"tom-and-jerry","name":"tom-and-jerry"}]}