{"id":588,"page":588,"slug":"ceo-of-hindustan-unilever-going-out-to-order-another-ad-to-mock-hinduism","title":"CEO of Hindustan Unilever going out to order another ad to mock Hinduism.","titleHi":"हिंदुस्तान यूनिलीवर के सीईओ ने हिंदू धर्म का मजाक उड़ाने के लिए एक और विज्ञापन का आदेश दिया।","imageUrl":"588_low.gif","ampImage":"588.gif","url":"https://gif-api.askgif.com/gif/id/588-en.json","dateCreated":"2019-03-10T14:33:12.544Z","dateModified":"0001-01-01T00:00:00","contributedBy":"AskGif","tags":[{"slug":"actor","name":"actor"},{"slug":"advertisement","name":"advertisement"},{"slug":"alauddin-khalji","name":"alauddin-khalji"},{"slug":"bollywood","name":"bollywood"},{"slug":"hinduism","name":"hinduism"},{"slug":"hindustan-unilever","name":"hindustan-unilever"},{"slug":"horse-rider","name":"horse-rider"},{"slug":"mad","name":"mad"},{"slug":"mock","name":"mock"},{"slug":"movie","name":"movie"},{"slug":"padmaavat","name":"padmaavat"},{"slug":"ranveer-singh","name":"ranveer-singh"},{"slug":"surf-excel","name":"surf-excel"},{"slug":"tyrant","name":"tyrant"}]}