{"id":600,"page":600,"slug":"when-someone-asks-me-how-is-the-life","title":"When someone asks me how is the life.","titleHi":"जब कोई मुझसे पूछता है कि जीवन कैसा है।","imageUrl":"600_low.gif","ampImage":"600.gif","url":"https://gif-api.askgif.com/gif/id/600-en.json","dateCreated":"2019-03-19T16:36:22.733Z","dateModified":"0001-01-01T00:00:00","contributedBy":"AskGif","tags":[{"slug":"actor","name":"actor"},{"slug":"american","name":"american"},{"slug":"arnold-schwarzenegger","name":"arnold-schwarzenegger"},{"slug":"hollywood","name":"hollywood"},{"slug":"how-is-life","name":"how-is-life"},{"slug":"movie","name":"movie"},{"slug":"politician","name":"politician"},{"slug":"terminator","name":"terminator"},{"slug":"terminator-2-judgement-day","name":"terminator-2-judgement-day"},{"slug":"thumbs-up","name":"thumbs-up"}]}