{"id":705,"page":705,"slug":"when-someone-puts-their-finger-over-my-screen-to-show-something","title":"When someone puts their finger over my screen to show something.","titleHi":"जब कोई कुछ दिखाने के लिए अपनी उंगली मेरी स्क्रीन पर डालता है।","imageUrl":"705_low.gif","ampImage":"705.gif","url":"https://gif-api.askgif.com/gif/id/705-en.json","dateCreated":"2019-05-01T08:00:42.553Z","dateModified":"0001-01-01T00:00:00","contributedBy":"AskGif","tags":[{"slug":"actor","name":"actor"},{"slug":"angry","name":"angry"},{"slug":"dirty","name":"dirty"},{"slug":"doctor","name":"doctor"},{"slug":"dr-john-watson","name":"dr-john-watson"},{"slug":"dr-watson","name":"dr-watson"},{"slug":"english-actor","name":"english-actor"},{"slug":"fuming","name":"fuming"},{"slug":"mad","name":"mad"},{"slug":"martin-freeman","name":"martin-freeman"},{"slug":"sherlock","name":"sherlock"},{"slug":"temper","name":"temper"},{"slug":"tv-show","name":"tv-show"},{"slug":"urge-to-kill","name":"urge-to-kill"}]}