{"id":858,"page":858,"slug":"when-a-teacher-and-a-student-start-arguing","title":"When a teacher and a student start arguing.","titleHi":"जब एक शिक्षक और एक छात्र बहस करने लगते हैं।","imageUrl":"858_low.gif","ampImage":"858.gif","url":"https://gif-api.askgif.com/gif/id/858-en.json","dateCreated":"2019-09-22T13:39:33.051Z","dateModified":"0001-01-01T00:00:00","contributedBy":"AskGif","tags":[{"slug":"arguing","name":"arguing"},{"slug":"argument","name":"argument"},{"slug":"deer","name":"deer"},{"slug":"keep-going","name":"keep-going"},{"slug":"lurking","name":"lurking"},{"slug":"munching","name":"munching"},{"slug":"popcorn","name":"popcorn"},{"slug":"student","name":"student"},{"slug":"teacher","name":"teacher"},{"slug":"watching","name":"watching"}]}