{"id":933,"page":933,"slug":"when-you-are-trying-to-hide-a-mistake-you-did","title":"When you are trying to hide a mistake you did.","titleHi":"जब आप एक गलती को छिपाने की कोशिश कर रहे हैं।","imageUrl":"933_low.gif","ampImage":"933.gif","url":"https://gif-api.askgif.com/gif/id/933-en.json","dateCreated":"2019-11-18T13:19:15.78Z","dateModified":"0001-01-01T00:00:00","contributedBy":"AskGif","tags":[{"slug":"actress","name":"actress"},{"slug":"betrayed","name":"betrayed"},{"slug":"hoax","name":"hoax"},{"slug":"hollywood","name":"hollywood"},{"slug":"kristen-stewart","name":"kristen-stewart"},{"slug":"mirror","name":"mirror"}]}