{"id":964,"page":964,"slug":"when-abdul-razzaq-says-that-he-would-have-easily-dominated-baby-bowler-bumrah","title":"When Abdul Razzaq says that he would have easily dominated 'baby bowler' Bumrah","titleHi":"जब अब्दुल रज्जाक कहते हैं कि वह आसानी से 'बेबी बॉलर' बुमराह पर हावी हो जाते थे","imageUrl":"964_low.gif","ampImage":"964.gif","url":"https://gif-api.askgif.com/gif/id/964-en.json","dateCreated":"2019-12-04T14:49:20.721Z","dateModified":"0001-01-01T00:00:00","contributedBy":"AskGif","tags":[{"slug":"abdul-razzaq","name":"abdul-razzaq"},{"slug":"actor","name":"actor"},{"slug":"angry","name":"angry"},{"slug":"anupam-kher","name":"anupam-kher"},{"slug":"baby-bowler","name":"baby-bowler"},{"slug":"bollywood","name":"bollywood"},{"slug":"jasprit-bumrah","name":"jasprit-bumrah"},{"slug":"wrong","name":"wrong"},{"slug":"you-are-wrong","name":"you-are-wrong"}]}