{"id":982,"page":982,"slug":"when-am-trying-to-escape-from-my-busy-life","title":"When am trying to escape from my busy life.","titleHi":"जब मैं अपने व्यस्त जीवन से भागने की कोशिश कर रहा हूं।","imageUrl":"982_low.gif","ampImage":"982.gif","url":"https://gif-api.askgif.com/gif/id/982-en.json","dateCreated":"2019-12-08T02:57:33.263Z","dateModified":"0001-01-01T00:00:00","contributedBy":"AskGif","tags":[{"slug":"actor","name":"actor"},{"slug":"arshad-warsi","name":"arshad-warsi"},{"slug":"bollywood","name":"bollywood"},{"slug":"bye","name":"bye"},{"slug":"escape","name":"escape"},{"slug":"jolly-llb","name":"jolly-llb"},{"slug":"lawyer","name":"lawyer"},{"slug":"trip","name":"trip"},{"slug":"vacation","name":"vacation"}]}