{"id":998,"page":998,"slug":"when-your-best-friend-is-clicking-the-photo-of-you","title":"When your best friend is clicking the photo of you.","titleHi":"जब आपका सबसे अच्छा दोस्त आपकी फोटो क्लिक कर रहा हो।","imageUrl":"998_low.gif","ampImage":"998.gif","url":"https://gif-api.askgif.com/gif/id/998-en.json","dateCreated":"2020-04-14T08:39:05.897Z","dateModified":"0001-01-01T00:00:00","contributedBy":"AskGif","tags":[{"slug":"actress","name":"actress"},{"slug":"aditi-rao-hydari","name":"aditi-rao-hydari"},{"slug":"best-friend","name":"best-friend"},{"slug":"bollywood","name":"bollywood"},{"slug":"indian","name":"indian"},{"slug":"model","name":"model"},{"slug":"modeling","name":"modeling"},{"slug":"photo-shoot","name":"photo-shoot"}]}