{"page":1395,"locale":"en","url":"https://gif-api.askgif.com/gif/id/1395-en.json","id":1395,"title":"I'm not just chaos.","imageUrl":"6312030c-0a0e-4534-88a1-c2a9b8accd41-UY49.gif","dateCreated":"2020-08-17T09:57:56.933Z","dateModified":"0001-01-01T00:00:00","contributedBy":"sumitc91","ampImage":null,"slug":"im-not-just-chaos","fetched_at":"2025-11-10T16:57:13.561Z","tags":[{"slug":"chaos","name":"chaos"},{"slug":"quotes","name":"quotes"},{"slug":"realization","name":"realization"},{"slug":"sad","name":"sad"},{"slug":"sorry","name":"sorry"},{"slug":"truth","name":"truth"}]}